setup.py
projectmanagement/__init__.py
projectmanagement.egg-info/PKG-INFO
projectmanagement.egg-info/SOURCES.txt
projectmanagement.egg-info/dependency_links.txt
projectmanagement.egg-info/top_level.txt