Metadata-Version: 2.1
Name: projectmanagement
Version: 0.0.1
Summary: Project Management
Author: Filippo Maria Ottaviani
Author-email: filippomariaottaviani@gmail.com
License: UNKNOWN
Platform: UNKNOWN
